iflow_mcp_searchapi_mcp_agent-1.0.0.dist-info/licenses/LICENSE
searchapi_mcp_agent/__init__.py
searchapi_mcp_agent/__main__.py
searchapi_mcp_agent/agent.py
searchapi_mcp_agent/mcp_server.py
searchapi_mcp_agent/task_manager.py
iflow_mcp_searchapi_mcp_agent-1.0.0.dist-info/METADATA
iflow_mcp_searchapi_mcp_agent-1.0.0.dist-info/WHEEL
iflow_mcp_searchapi_mcp_agent-1.0.0.dist-info/entry_points.txt
iflow_mcp_searchapi_mcp_agent-1.0.0.dist-info/top_level.txt
iflow_mcp_searchapi_mcp_agent-1.0.0.dist-info/RECORD
