Metadata-Version: 2.4
Name: iflow-mcp_searchapi-mcp-agent
Version: 1.0.0
Summary: SearchAPI MCP Agent with A2A support - provides Google search, maps, flights, hotels, videos search functionality
Author-email: IFLOW <iflow@example.com>
License: MIT
Project-URL: Homepage, https://github.com/iflow-mcp/searchapi-mcp-agent
Project-URL: Repository, https://github.com/iflow-mcp/searchapi-mcp-agent
Project-URL: Issues, https://github.com/iflow-mcp/searchapi-mcp-agent/issues
Classifier: Development Status :: 4 - Beta
Classifier: Intended Audience :: Developers
Classifier: License :: OSI Approved :: MIT License
Classifier: Programming Language :: Python :: 3
Classifier: Programming Language :: Python :: 3.9
Classifier: Programming Language :: Python :: 3.10
Classifier: Programming Language :: Python :: 3.11
Classifier: Programming Language :: Python :: 3.12
Requires-Python: >=3.9
License-File: LICENSE
Requires-Dist: python-dotenv>=1.0.0
Requires-Dist: click>=8.0.0
Requires-Dist: google-generativeai>=0.3.0
Requires-Dist: httpx>=0.24.0
Requires-Dist: mcp>=0.5.0
Requires-Dist: pydantic>=2.0.0
Requires-Dist: fastapi>=0.100.0
Requires-Dist: uvicorn>=0.23.0
Dynamic: license-file
